Metadata-Version: 2.1
Name: odoo-addon-account_invoice_supplierinfo_update
Version: 18.0.1.1.0.3
Requires-Python: >=3.10
Requires-Dist: odoo==18.0.*
Summary: In the supplier invoice, automatically updates all products whose unit price on the line is different from the supplier price
Home-page: https://github.com/OCA/account-invoicing
License: AGPL-3
Author: Akretion, GRAP, Odoo Community Association (OCA)
Author-email: support@odoo-community.org
Classifier: Programming Language :: Python
Classifier: Framework :: Odoo
Classifier: Framework :: Odoo :: 18.0
Classifier: License :: OSI Approved :: GNU Affero General Public License v3
